configredis/__init__.py
configredis/setconf.py
configredis/setredis.py
config_redis-0.2.12.dist-info/LICENSE
config_redis-0.2.12.dist-info/METADATA
config_redis-0.2.12.dist-info/WHEEL
config_redis-0.2.12.dist-info/top_level.txt
config_redis-0.2.12.dist-info/RECORD
