Metadata-Version: 2.1
Name: config-redis
Version: 0.2.12
Summary: Get proj config args from redis
Home-page: https://github.com/x254724521/proj_config
Author: Supplayer
Author-email: x254724521@hotmail.com
License: UNKNOWN
Platform: UNKNOWN
Classifier: Programming Language :: Python :: 3
Classifier: License :: OSI Approved :: MIT License
Classifier: Operating System :: OS Independent
Requires-Python: >=3.6
License-File: LICENSE
Requires-Dist: redis
